CHANGELOG.txt
LICENSE.txt
MANIFEST.in
README.txt
setup.py
KPIs/__init__.py
KPIs.egg-info/PKG-INFO
KPIs.egg-info/SOURCES.txt
KPIs.egg-info/dependency_links.txt
KPIs.egg-info/requires.txt
KPIs.egg-info/top_level.txt