Metadata-Version: 2.1
Name: KPIs
Version: 0.1
Summary: Key Performance Indicator and Backtesting
Home-page: 
Author: Rakshit Maggon
Author-email: rakshitmaggon70@gmail.com
License: MIT
Keywords: Backtesting
Classifier: Development Status :: 5 - Production/Stable
Classifier: Intended Audience :: Education
Classifier: Operating System :: Microsoft :: Windows :: Windows 10
Classifier: License :: OSI Approved :: MIT License
Classifier: Programming Language :: Python :: 3
Requires-Python: >=3.6
License-File: LICENSE.txt
